aion_xtensions_chronos/__init__.py
tests/__init__.py
tests/test_chronos.py
aion_chronos-0.1.dist-info/METADATA
aion_chronos-0.1.dist-info/WHEEL
aion_chronos-0.1.dist-info/top_level.txt
aion_chronos-0.1.dist-info/RECORD
