Metadata-Version: 2.1
Name: aion_chronos
Version: 0.1
Summary: Aion Xtensions Chronos to generate AX mappings based on modules and use cases.
Home-page: https://github.com/yourusername/aion-xtensions-chronos
Author: Aion
Author-email: aion@hcl.com
Classifier: Programming Language :: Python :: 3
Classifier: License :: OSI Approved :: MIT License
Classifier: Operating System :: OS Independent
Requires-Python: >=3.6
